<keymap version="1" name="Mac OS X 10.5+ copy" parent="Mac OS X 10.5+">
  <action id="ActivateDebugToolWindow" />
  <action id="ActivateFavoritesToolWindow" />
  <action id="ActivateFindToolWindow" />
  <action id="ActivateRunToolWindow">
    <keyboard-shortcut first-keystroke="meta 3" />
  </action>
  <action id="ActivateTerminalToolWindow">
    <keyboard-shortcut first-keystroke="meta 4" />
  </action>
  <action id="CompareTwoFiles" />
  <action id="Diff.ShowDiff" />
  <action id="Diff.ShowSettingsPopup" />
  <action id="DuplicatesForm.SendToRight" />
  <action id="EditorDuplicate" />
  <action id="EditorSplitLine" />
  <action id="FileChooser.GotoDesktop" />
  <action id="FileChooser.GotoModule" />
  <action id="FileChooser.GotoProject" />
  <action id="IpnbRunCellInplaceAction" />
  <action id="LocalHistory">
    <keyboard-shortcut first-keystroke="shift meta l" />
  </action>
  <action id="LocalHistory.ShowHistory">
    <keyboard-shortcut first-keystroke="ctrl meta l" />
  </action>
  <action id="Run">
    <keyboard-shortcut first-keystroke="ctrl r" />
    <keyboard-shortcut first-keystroke="meta i" />
  </action>
  <action id="SendEOF" />
  <action id="ShelvedChanges.Diff" />
  <action id="SplitHorizontally">
    <keyboard-shortcut first-keystroke="shift meta d" />
  </action>
  <action id="SplitVertically">
    <keyboard-shortcut first-keystroke="meta d" />
  </action>
  <action id="SwitchApply">
    <keyboard-shortcut first-keystroke="ctrl alt enter" />
  </action>
  <action id="SwitchDown">
    <keyboard-shortcut first-keystroke="ctrl alt down" />
  </action>
  <action id="SwitchLeft">
    <keyboard-shortcut first-keystroke="ctrl alt left" />
  </action>
  <action id="SwitchRight">
    <keyboard-shortcut first-keystroke="ctrl alt right" />
  </action>
  <action id="SwitchUp">
    <keyboard-shortcut first-keystroke="ctrl alt up" />
  </action>
  <action id="Uml.ShowDiff" />
  <action id="ViewSource" />
  <action id="com.jetbrains.plugins.remotesdk.console.RunSshConsoleAction">
    <keyboard-shortcut first-keystroke="meta 5" />
  </action>
  <action id="com.jetbrains.python.console.RunPythonConsoleAction">
    <keyboard-shortcut first-keystroke="meta 2" />
  </action>
  <action id="openAssertEqualsDiff" />
</keymap>